pyexodus/RELEASE-VERSION
pyexodus/__init__.py
pyexodus/core.py
pyexodus/version.py
pyexodus/tests/__init__.py
pyexodus/tests/test_reading_exodus.py
pyexodus/tests/test_writing_exodus.py
pyexodus-0.1.3.dist-info/LICENSE.txt
pyexodus-0.1.3.dist-info/METADATA
pyexodus-0.1.3.dist-info/WHEEL
pyexodus-0.1.3.dist-info/top_level.txt
pyexodus-0.1.3.dist-info/RECORD
